core_abb/__init__.py
core_abb-0.0.1.dist-info/LICENSE
core_abb-0.0.1.dist-info/METADATA
core_abb-0.0.1.dist-info/WHEEL
core_abb-0.0.1.dist-info/top_level.txt
core_abb-0.0.1.dist-info/RECORD
