Metadata-Version: 2.1
Name: core-abb
Version: 0.0.1
Summary: A utility package for ABB
Home-page: https://github.com/bonnybabukachappilly/ros2tcp
Author: Bonny Babu
Author-email: bonnybabukachappilly@gmail.com
License: GNU GENERAL PUBLIC LICENSE Version 3
Platform: UNKNOWN
Classifier: Programming Language :: Python :: 3
Classifier: Programming Language :: Python :: 3.10
Classifier: License :: OSI Approved :: GNU General Public License v3 (GPLv3)
Classifier: Operating System :: Unix
Requires-Python: >=3.10
License-File: LICENSE
Provides-Extra: dev
Requires-Dist: flake8 (>=7.1.1) ; extra == 'dev'
Requires-Dist: tox (>=4.23.2) ; extra == 'dev'
Requires-Dist: pytest (>=8.3.4) ; extra == 'dev'
Requires-Dist: pytest-cov (>=6.0.0) ; extra == 'dev'
Requires-Dist: mypy (>=1.13.0) ; extra == 'dev'
Requires-Dist: check-manifest (>=0.50) ; extra == 'dev'
